{
  "attributes": {
    "jarm": "3fd3fd15d3fd3fd00042d42d00000061256d32ed7779c14686ad100544dc8d",
    "network": "157.245.0.0/16",
    "last_https_certificate_date": 1663962653,
    "tags": [],
    "whois": "inetnum: 157.0.0.0 - 157.255.255.255\nnetname: ERX-NETBLOCK\ndescr: Early registration addresses\ncountry: AU\nadmin-c: IANA1-AP\ntech-c: IANA1-AP\nabuse-c: AA1452-AP\nstatus: ALLOCATED PORTABLE\nremarks: ------------------------------------------------------\nremarks: Important:\nremarks:\nremarks: Networks in this range were allocated by InterNIC\nremarks: prior to the formation of Regional Internet\nremarks: Registries (RIRs): AfriNIC, APNIC, ARIN, LACNIC and RIPE NCC.\nremarks:\nremarks: Address ranges from this historical space have now\nremarks: been transferred to the appropriate RIR database.remarks:\nremarks: If your search has returned this record, it means the\nremarks: address range is not administered by APNIC.\nremarks:\nremarks: Instead, please search one of the following databases:\nremarks:\nremarks: - AfriNIC (Africa)\nremarks: website: http://www.afrinic.net/\nremarks: command line: whois.afrinic.net\nremarks:\nremarks: - ARIN (Northern America)\nremarks: website: http://www.arin.net/\nremarks: command line: whois.arin.net\nremarks:\nremarks: - LACNIC (Latin America and the Carribean)\nremarks: website: http://www.lacnic.net/\nremarks: command line: whois.lacnic.net\nremarks:\nremarks: - RIPE NCC (Europe)\nremarks: website: http://www.ripe.net/\nremarks: command line: whois.ripe.net\nremarks:\nremarks: For information on the Early Registration Transfer\nremarks: (ERX) project, see:\nremarks:\nremarks: http://www.apnic.net/db/erx\nremarks:\nremarks: ------------------------------------------------------\nmnt-by: APNIC-HM\nmnt-lower: APNIC-HM\nmnt-irt: IRT-APNIC-AP\nlast-modified: 2020-07-20T05:26:35Z\nsource: APNIC\nirt: IRT-APNIC-AP\naddress: Brisbane, Australia\ne-mail: helpdesk@apnic.net\nabuse-mailbox: helpdesk@apnic.net\nadmin-c: HM20-AP\ntech-c: NO4-AP\nauth: # Filtered\nremarks: APNIC is a Regional Internet Registry.\nremarks: We do not operate the referring network and\nremarks: are unable to investigate complaints of network abuse.\nremarks: For information about IRT, see www.apnic.net/irt\nremarks: helpdesk@apnic.net was validated on 2020-02-03\nmnt-by: APNIC-HM\nlast-modified: 2023-08-18T00:42:38Z\nsource: APNIC\nrole: ABUSE APNICAP\naddress: Brisbane, Australia\ncountry: ZZ\nphone: +000000000\ne-mail: helpdesk@apnic.net\nadmin-c: HM20-AP\ntech-c: NO4-AP\nnic-hdl: AA1452-AP\nremarks: Generated from irt object IRT-APNIC-AP\nremarks: helpdesk@apnic.net was validated on 2020-02-03\nabuse-mailbox: helpdesk@apnic.net\nmnt-by: APNIC-ABUSE\nlast-modified: 2023-08-18T19:08:30Z\nsource: APNIC\nrole: Internet Assigned Numbers Authority\naddress: see http://www.iana.org.\nadmin-c: IANA1-AP\ntech-c: IANA1-AP\nnic-hdl: IANA1-AP\nremarks: For more information on IANA services\nremarks: go to IANA web site at http://www.iana.org.\nmnt-by: MAINT-APNIC-AP\nlast-modified: 2018-06-22T22:34:30Z\nsource: APNIC\n",
    "last_analysis_date": 1694371157,
    "as_owner": "DIGITALOCEAN-ASN",
    "last_analysis_stats": {
      "harmless": 63,
      "malicious": 3,
      "suspicious": 0,
      "undetected": 23,
      "timeout": 0
    },
    "asn": 14061,
    "whois_date": 1693927547,
    "reputation": 0,
    "last_analysis_results": {
      "Bkav": {
        "category": "undetected",
        "result": "unrated",
        "method": "blacklist",
        "engine_name": "Bkav"
      },
      "CMC Threat Intelligence": {
        "category": "harmless",
        "result": "clean",
        "method": "blacklist",
        "engine_name": "CMC Threat Intelligence"
      },
      "Snort IP sample list": {
        "category": "harmless",
        "result": "clean",
        "method": "blacklist",
        "engine_name": "Snort IP sample list"
      },
      "0xSI_f33d": {
        "category": "undetected",
        "result": "unrated",
        "method": "blacklist",
        "engine_name": "0xSI_f33d"
      },
      "ViriBack": {
        "category": "harmless",
        "result": "clean",
        "method": "blacklist",
        "engine_name": "ViriBack"
      },
      "PhishLabs": {
        "category": "undetected",
        "result": "unrated",
        "method": "blacklist",
        "engine_name": "PhishLabs"
      },
      "K7AntiVirus": {
        "category": "harmless",
        "result": "clean",
        "method": "blacklist",
        "engine_name": "K7AntiVirus"
      },
      "CINS Army": {
        "category": "harmless",
        "result": "clean",
        "method": "blacklist",
        "engine_name": "CINS Army"
      },
      "Quttera": {
        "category": "harmless",
        "result": "clean",
        "method": "blacklist",
        "engine_name": "Quttera"
      },
      "PrecisionSec": {
        "category": "undetected",
        "result": "unrated",
        "method": "blacklist",
        "engine_name": "PrecisionSec"
      },
      "OpenPhish": {
        "category": "harmless",
        "result": "clean",
        "method": "blacklist",
        "engine_name": "OpenPhish"
      },
      "VX Vault": {
        "category": "harmless",
        "result": "clean",
        "method": "blacklist",
        "engine_name": "VX Vault"
      },
      "ArcSight Threat Intelligence": {
        "category": "undetected",
        "result": "unrated",
        "method": "blacklist",
        "engine_name": "ArcSight Threat Intelligence"
      },
      "Scantitan": {
        "category": "harmless",
        "result": "clean",
        "method": "blacklist",
        "engine_name": "Scantitan"
      },
      "AlienVault": {
        "category": "harmless",
        "result": "clean",
        "method": "blacklist",
        "engine_name": "AlienVault"
      },
      "Sophos": {
        "category": "harmless",
        "result": "clean",
        "method": "blacklist",
        "engine_name": "Sophos"
      },
      "Phishtank": {
        "category": "harmless",
        "result": "clean",
        "method": "blacklist",
        "engine_name": "Phishtank"
      },
      "Cyan": {
        "category": "undetected",
        "result": "unrated",
        "method": "blacklist",
        "engine_name": "Cyan"
      },
      "Spam404": {
        "category": "harmless",
        "result": "clean",
        "method": "blacklist",
        "engine_name": "Spam404"
      },
      "SecureBrain": {
        "category": "undetected",
        "result": "unrated",
        "method": "blacklist",
        "engine_name": "SecureBrain"
      },
      "CRDF": {
        "category": "malicious",
        "result": "malicious",
        "method": "blacklist",
        "engine_name": "CRDF"
      },
      "Fortinet": {
        "category": "malicious",
        "result": "malware",
        "method": "blacklist",
        "engine_name": "Fortinet"
      },
      "alphaMountain.ai": {
        "category": "harmless",
        "result": "clean",
        "method": "blacklist",
        "engine_name": "alphaMountain.ai"
      },
      "Lionic": {
        "category": "harmless",
        "result": "clean",
        "method": "blacklist",
        "engine_name": "Lionic"
      },
      "Cyble": {
        "category": "harmless",
        "result": "clean",
        "method": "blacklist",
        "engine_name": "Cyble"
      },
      "Seclookup": {
        "category": "harmless",
        "result": "clean",
        "method": "blacklist",
        "engine_name": "Seclookup"
      },
      "Xcitium Verdict Cloud": {
        "category": "harmless",
        "result": "clean",
        "method": "blacklist",
        "engine_name": "Xcitium Verdict Cloud"
      },
      "Google Safebrowsing": {
        "category": "harmless",
        "result": "clean",
        "method": "blacklist",
        "engine_name": "Google Safebrowsing"
      },
      "SafeToOpen": {
        "category": "undetected",
        "result": "unrated",
        "method": "blacklist",
        "engine_name": "SafeToOpen"
      },
      "ADMINUSLabs": {
        "category": "harmless",
        "result": "clean",
        "method": "blacklist",
        "engine_name": "ADMINUSLabs"
      },
      "ESTsecurity": {
        "category": "harmless",
        "result": "clean",
        "method": "blacklist",
        "engine_name": "ESTsecurity"
      },
      "Juniper Networks": {
        "category": "harmless",
        "result": "clean",
        "method": "blacklist",
        "engine_name": "Juniper Networks"
      },
      "Heimdal Security": {
        "category": "harmless",
        "result": "clean",
        "method": "blacklist",
        "engine_name": "Heimdal Security"
      },
      "AutoShun": {
        "category": "undetected",
        "result": "unrated",
        "method": "blacklist",
        "engine_name": "AutoShun"
      },
      "Trustwave": {
        "category": "harmless",
        "result": "clean",
        "method": "blacklist",
        "engine_name": "Trustwave"
      },
      "CyRadar": {
        "category": "harmless",
        "result": "clean",
        "method": "blacklist",
        "engine_name": "CyRadar"
      },
      "Dr.Web": {
        "category": "harmless",
        "result": "clean",
        "method": "blacklist",
        "engine_name": "Dr.Web"
      },
      "Emsisoft": {
        "category": "harmless",
        "result": "clean",
        "method": "blacklist",
        "engine_name": "Emsisoft"
      },
      "Abusix": {
        "category": "harmless",
        "result": "clean",
        "method": "blacklist",
        "engine_name": "Abusix"
      },
      "Webroot": {
        "category": "harmless",
        "result": "clean",
        "method": "blacklist",
        "engine_name": "Webroot"
      },
      "Avira": {
        "category": "harmless",
        "result": "clean",
        "method": "blacklist",
        "engine_name": "Avira"
      },
      "securolytics": {
        "category": "harmless",
        "result": "clean",
        "method": "blacklist",
        "engine_name": "securolytics"
      },
      "Antiy-AVL": {
        "category": "harmless",
        "result": "clean",
        "method": "blacklist",
        "engine_name": "Antiy-AVL"
      },
      "AlphaSOC": {
        "category": "undetected",
        "result": "unrated",
        "method": "blacklist",
        "engine_name": "AlphaSOC"
      },
      "Acronis": {
        "category": "harmless",
        "result": "clean",
        "method": "blacklist",
        "engine_name": "Acronis"
      },
      "Quick Heal": {
        "category": "harmless",
        "result": "clean",
        "method": "blacklist",
        "engine_name": "Quick Heal"
      },
      "URLQuery": {
        "category": "undetected",
        "result": "unrated",
        "method": "blacklist",
        "engine_name": "URLQuery"
      },
      "Ermes": {
        "category": "undetected",
        "result": "unrated",
        "method": "blacklist",
        "engine_name": "Ermes"
      },
      "Viettel Threat Intelligence": {
        "category": "harmless",
        "result": "clean",
        "method": "blacklist",
        "engine_name": "Viettel Threat Intelligence"
      },
      "DNS8": {
        "category": "harmless",
        "result": "clean",
        "method": "blacklist",
        "engine_name": "DNS8"
      },
      "AILabs (MONITORAPP)": {
        "category": "harmless",
        "result": "clean",
        "method": "blacklist",
        "engine_name": "AILabs (MONITORAPP)"
      },
      "benkow.cc": {
        "category": "harmless",
        "result": "clean",
        "method": "blacklist",
        "engine_name": "benkow.cc"
      },
      "EmergingThreats": {
        "category": "harmless",
        "result": "clean",
        "method": "blacklist",
        "engine_name": "EmergingThreats"
      },
      "Chong Lua Dao": {
        "category": "harmless",
        "result": "clean",
        "method": "blacklist",
        "engine_name": "Chong Lua Dao"
      },
      "Yandex Safebrowsing": {
        "category": "harmless",
        "result": "clean",
        "method": "blacklist",
        "engine_name": "Yandex Safebrowsing"
      },
      "Lumu": {
        "category": "undetected",
        "result": "unrated",
        "method": "blacklist",
        "engine_name": "Lumu"
      },
      "zvelo": {
        "category": "undetected",
        "result": "unrated",
        "method": "blacklist",
        "engine_name": "zvelo"
      },
      "Kaspersky": {
        "category": "undetected",
        "result": "unrated",
        "method": "blacklist",
        "engine_name": "Kaspersky"
      },
      "Segasec": {
        "category": "undetected",
        "result": "unrated",
        "method": "blacklist",
        "engine_name": "Segasec"
      },
      "Sucuri SiteCheck": {
        "category": "harmless",
        "result": "clean",
        "method": "blacklist",
        "engine_name": "Sucuri SiteCheck"
      },
      "desenmascara.me": {
        "category": "harmless",
        "result": "clean",
        "method": "blacklist",
        "engine_name": "desenmascara.me"
      },
      "CrowdSec": {
        "category": "undetected",
        "result": "unrated",
        "method": "blacklist",
        "engine_name": "CrowdSec"
      },
      "Cluster25": {
        "category": "undetected",
        "result": "unrated",
        "method": "blacklist",
        "engine_name": "Cluster25"
      },
      "SOCRadar": {
        "category": "harmless",
        "result": "clean",
        "method": "blacklist",
        "engine_name": "SOCRadar"
      },
      "URLhaus": {
        "category": "harmless",
        "result": "clean",
        "method": "blacklist",
        "engine_name": "URLhaus"
      },
      "PREBYTES": {
        "category": "harmless",
        "result": "clean",
        "method": "blacklist",
        "engine_name": "PREBYTES"
      },
      "StopForumSpam": {
        "category": "harmless",
        "result": "clean",
        "method": "blacklist",
        "engine_name": "StopForumSpam"
      },
      "Blueliv": {
        "category": "harmless",
        "result": "clean",
        "method": "blacklist",
        "engine_name": "Blueliv"
      },
      "Netcraft": {
        "category": "undetected",
        "result": "unrated",
        "method": "blacklist",
        "engine_name": "Netcraft"
      },
      "ZeroCERT": {
        "category": "harmless",
        "result": "clean",
        "method": "blacklist",
        "engine_name": "ZeroCERT"
      },
      "Phishing Database": {
        "category": "harmless",
        "result": "clean",
        "method": "blacklist",
        "engine_name": "Phishing Database"
      },
      "MalwarePatrol": {
        "category": "harmless",
        "result": "clean",
        "method": "blacklist",
        "engine_name": "MalwarePatrol"
      },
      "IPsum": {
        "category": "harmless",
        "result": "clean",
        "method": "blacklist",
        "engine_name": "IPsum"
      },
      "Malwared": {
        "category": "harmless",
        "result": "clean",
        "method": "blacklist",
        "engine_name": "Malwared"
      },
      "BitDefender": {
        "category": "harmless",
        "result": "clean",
        "method": "blacklist",
        "engine_name": "BitDefender"
      },
      "GreenSnow": {
        "category": "harmless",
        "result": "clean",
        "method": "blacklist",
        "engine_name": "GreenSnow"
      },
      "G-Data": {
        "category": "harmless",
        "result": "clean",
        "method": "blacklist",
        "engine_name": "G-Data"
      },
      "VIPRE": {
        "category": "undetected",
        "result": "unrated",
        "method": "blacklist",
        "engine_name": "VIPRE"
      },
      "SCUMWARE.org": {
        "category": "harmless",
        "result": "clean",
        "method": "blacklist",
        "engine_name": "SCUMWARE.org"
      },
      "PhishFort": {
        "category": "undetected",
        "result": "unrated",
        "method": "blacklist",
        "engine_name": "PhishFort"
      },
      "malwares.com URL checker": {
        "category": "harmless",
        "result": "clean",
        "method": "blacklist",
        "engine_name": "malwares.com URL checker"
      },
      "Forcepoint ThreatSeeker": {
        "category": "undetected",
        "result": "unrated",
        "method": "blacklist",
        "engine_name": "Forcepoint ThreatSeeker"
      },
      "Criminal IP": {
        "category": "malicious",
        "result": "malicious",
        "method": "blacklist",
        "engine_name": "Criminal IP"
      },
      "Certego": {
        "category": "harmless",
        "result": "clean",
        "method": "blacklist",
        "engine_name": "Certego"
      },
      "ESET": {
        "category": "harmless",
        "result": "clean",
        "method": "blacklist",
        "engine_name": "ESET"
      },
      "Threatsourcing": {
        "category": "harmless",
        "result": "clean",
        "method": "blacklist",
        "engine_name": "Threatsourcing"
      },
      "ThreatHive": {
        "category": "harmless",
        "result": "clean",
        "method": "blacklist",
        "engine_name": "ThreatHive"
      },
      "Bfore.Ai PreCrime": {
        "category": "harmless",
        "result": "clean",
        "method": "blacklist",
        "engine_name": "Bfore.Ai PreCrime"
      }
    },
    "country": "IN",
    "last_modification_date": 1694374859,
    "regional_internet_registry": "APNIC",
    "last_https_certificate": {
      "public_key": {
        "rsa": {
          "key_size": 2048,
          "modulus": "00dd6ac8923c46d52bb1d36a9c9e3bb85bcb4034fd9df20cca74b6466bd9558809b0fa98e9ba9481188322884532d72fc602227c4d57d095a70d8fe893f7610d391f560047c51cf011d82ed91cdb00e7738ad6b21883b8e64bb3dd62788bc93687e574bb3d75552757d0145b50d050e477fdbb642689efd0a4a40a639b863fdbd0e2543cac12aca18a06cc947ad08fcb316ebd3a38462ece1bdb2b6c3503f05d7492358b6be032d7ec84b79f46fc18d88c87abc0ab5dbc36191976b3170c9de12167272b3479a672b756469cf91f190adf9bdedcace7160c95b811cf3cb5dd0f682758c5c2e633cc7614ce6d4f5483e94189b99579287b6f33fbd7528f9e736dc1",
          "exponent": "010001"
        },
        "algorithm": "RSA"
      },
      "thumbprint_sha256": "1cf20c135cf54392b0473e734e84391d58eca9ffcee951f166cfaec4b59b1da1",
      "tags": [],
      "signature_algorithm": "sha256RSA",
      "subject": {
        "CN": "astoria.ke"
      },
      "validity": {
        "not_after": "2022-12-22 18:41:19",
        "not_before": "2022-09-23 18:41:20"
      },
      "version": "V3",
      "extensions": {
        "certificate_policies": [
          "2.23.140.1.2.1",
          "1.3.6.1.4.1.44947.1.1.1"
        ],
        "extended_key_usage": [
          "serverAuth",
          "clientAuth"
        ],
        "tags": [],
        "subject_alternative_name": [
          "astoria.ke",
          "www.astoria.ke"
        ],
        "authority_key_identifier": {
          "keyid": "142eb317b75856cbae500940e61faf9d8b14c2c6"
        },
        "ca_information_access": {
          "CA Issuers": "http://r3.i.lencr.org/",
          "OCSP": "http://r3.o.lencr.org"
        },
        "subject_key_identifier": "c610407ba9a8455268cb516694183f453aa3154c",
        "key_usage": [
          "ff"
        ],
        "1.3.6.1.4.1.11129.2.4.2": "0481f200f000760041c8cab1df22464a10c6a13a0942875e4e318b1b03ebeb4b",
        "CA": true
      },
      "cert_signature": {
        "signature_algorithm": "sha256RSA",
        "signature": "377787c0b688b64a32c5de0e180fb53d7a31a5a7ece5a5f4c583eb9ec7a364be7b32c3333e06ab742caa8d776b33b8812129230f4f71900eda0670a892d5974e7d0d61c234c18afdf97dc6bd9b33646bcbbb9593d2bca249ae3cc763acf9353b7bfdef66a1548929ffb34bfa358ae38c37ff21073692a3544bb6ed017f0b2f6d2212248610fd8ff1a5962b45542349caf28c86daa6c8f3f3ed297068c224e4ee0719a5b7af697930837c59e6c71a2087510f2f52e131ab1071bc8dad41795a450c920985b47dfa83065e27a2504c91ab574a4f6a13e0c29a0b64889bdc42a7b7d48e033714dd05e24ec5931ec9896b623ab805c46dfdc998f1ee95476f10798a"
      },
      "serial_number": "0327c92f6ae0314ed83213ea1fab69727d20",
      "thumbprint": "9ce3cfe4451a247cec33886c60be322fb77bc03f",
      "issuer": {
        "C": "US",
        "CN": "R3",
        "O": "Let's Encrypt"
      },
      "size": 1326
    },
    "continent": "AS",
    "total_votes": {
      "harmless": 0,
      "malicious": 0
    }
  },
  "type": "ip_address",
  "id": "157.245.98.22",
  "links": {
    "self": "https://www.virustotal.com/api/v3/ip_addresses/157.245.98.22"
  }
}