{
  "attributes": {
    "jarm": "05d02d20d21d20d05c05d02d05d20d74fcf6501ae7a92319e575bfafd2a827",
    "network": "84.238.196.0/22",
    "last_https_certificate_date": 1694433987,
    "tags": [
      "self-signed"
    ],
    "whois": "inetnum: 84.238.197.0 - 84.238.203.255\nnetname: customers203\ncountry: BG\nadmin-c: MM34599-RIPE\ntech-c: MM34599-RIPE\nstatus: ASSIGNED PA\nmnt-by: multimedia-bg\ncreated: 2018-08-14T12:44:25Z\nlast-modified: 2018-08-14T12:44:25Z\nsource: RIPE\nperson: Milen Mladenov\naddress: Bulgaria, Sofia, Zona B18\nphone: +359895554578\nnic-hdl: MM34599-RIPE\nmnt-by: multimedia-bg\ncreated: 2012-10-09T12:07:21Z\nlast-modified: 2012-10-09T12:07:23Z\nsource: RIPE # Filtered\nroute: 84.238.196.0/22\ndescr: Multimedia-BG\norigin: AS47402\nmnt-by: multimedia-bg\ncreated: 2013-01-11T09:29:24Z\nlast-modified: 2013-01-11T09:29:24Z\nsource: RIPE\n",
    "last_analysis_date": 1694433973,
    "as_owner": "Multimedia BG EOOD",
    "last_analysis_stats": {
      "harmless": 63,
      "malicious": 3,
      "suspicious": 1,
      "undetected": 22,
      "timeout": 0
    },
    "asn": 47402,
    "whois_date": 1694433987,
    "reputation": 0,
    "last_analysis_results": {
      "Bkav": {
        "category": "undetected",
        "result": "unrated",
        "method": "blacklist",
        "engine_name": "Bkav"
      },
      "CMC Threat Intelligence": {
        "category": "harmless",
        "result": "clean",
        "method": "blacklist",
        "engine_name": "CMC Threat Intelligence"
      },
      "Snort IP sample list": {
        "category": "harmless",
        "result": "clean",
        "method": "blacklist",
        "engine_name": "Snort IP sample list"
      },
      "0xSI_f33d": {
        "category": "undetected",
        "result": "unrated",
        "method": "blacklist",
        "engine_name": "0xSI_f33d"
      },
      "ViriBack": {
        "category": "harmless",
        "result": "clean",
        "method": "blacklist",
        "engine_name": "ViriBack"
      },
      "PhishLabs": {
        "category": "undetected",
        "result": "unrated",
        "method": "blacklist",
        "engine_name": "PhishLabs"
      },
      "K7AntiVirus": {
        "category": "harmless",
        "result": "clean",
        "method": "blacklist",
        "engine_name": "K7AntiVirus"
      },
      "CINS Army": {
        "category": "harmless",
        "result": "clean",
        "method": "blacklist",
        "engine_name": "CINS Army"
      },
      "Quttera": {
        "category": "harmless",
        "result": "clean",
        "method": "blacklist",
        "engine_name": "Quttera"
      },
      "PrecisionSec": {
        "category": "undetected",
        "result": "unrated",
        "method": "blacklist",
        "engine_name": "PrecisionSec"
      },
      "OpenPhish": {
        "category": "harmless",
        "result": "clean",
        "method": "blacklist",
        "engine_name": "OpenPhish"
      },
      "VX Vault": {
        "category": "harmless",
        "result": "clean",
        "method": "blacklist",
        "engine_name": "VX Vault"
      },
      "ArcSight Threat Intelligence": {
        "category": "undetected",
        "result": "unrated",
        "method": "blacklist",
        "engine_name": "ArcSight Threat Intelligence"
      },
      "Scantitan": {
        "category": "harmless",
        "result": "clean",
        "method": "blacklist",
        "engine_name": "Scantitan"
      },
      "AlienVault": {
        "category": "harmless",
        "result": "clean",
        "method": "blacklist",
        "engine_name": "AlienVault"
      },
      "Sophos": {
        "category": "harmless",
        "result": "clean",
        "method": "blacklist",
        "engine_name": "Sophos"
      },
      "Phishtank": {
        "category": "harmless",
        "result": "clean",
        "method": "blacklist",
        "engine_name": "Phishtank"
      },
      "Cyan": {
        "category": "undetected",
        "result": "unrated",
        "method": "blacklist",
        "engine_name": "Cyan"
      },
      "Spam404": {
        "category": "harmless",
        "result": "clean",
        "method": "blacklist",
        "engine_name": "Spam404"
      },
      "SecureBrain": {
        "category": "harmless",
        "result": "clean",
        "method": "blacklist",
        "engine_name": "SecureBrain"
      },
      "CRDF": {
        "category": "harmless",
        "result": "clean",
        "method": "blacklist",
        "engine_name": "CRDF"
      },
      "Fortinet": {
        "category": "malicious",
        "result": "malware",
        "method": "blacklist",
        "engine_name": "Fortinet"
      },
      "alphaMountain.ai": {
        "category": "harmless",
        "result": "clean",
        "method": "blacklist",
        "engine_name": "alphaMountain.ai"
      },
      "Lionic": {
        "category": "harmless",
        "result": "clean",
        "method": "blacklist",
        "engine_name": "Lionic"
      },
      "Cyble": {
        "category": "harmless",
        "result": "clean",
        "method": "blacklist",
        "engine_name": "Cyble"
      },
      "Seclookup": {
        "category": "harmless",
        "result": "clean",
        "method": "blacklist",
        "engine_name": "Seclookup"
      },
      "Xcitium Verdict Cloud": {
        "category": "harmless",
        "result": "clean",
        "method": "blacklist",
        "engine_name": "Xcitium Verdict Cloud"
      },
      "Google Safebrowsing": {
        "category": "harmless",
        "result": "clean",
        "method": "blacklist",
        "engine_name": "Google Safebrowsing"
      },
      "SafeToOpen": {
        "category": "undetected",
        "result": "unrated",
        "method": "blacklist",
        "engine_name": "SafeToOpen"
      },
      "ADMINUSLabs": {
        "category": "harmless",
        "result": "clean",
        "method": "blacklist",
        "engine_name": "ADMINUSLabs"
      },
      "ESTsecurity": {
        "category": "harmless",
        "result": "clean",
        "method": "blacklist",
        "engine_name": "ESTsecurity"
      },
      "Juniper Networks": {
        "category": "harmless",
        "result": "clean",
        "method": "blacklist",
        "engine_name": "Juniper Networks"
      },
      "Heimdal Security": {
        "category": "harmless",
        "result": "clean",
        "method": "blacklist",
        "engine_name": "Heimdal Security"
      },
      "AutoShun": {
        "category": "undetected",
        "result": "unrated",
        "method": "blacklist",
        "engine_name": "AutoShun"
      },
      "Trustwave": {
        "category": "harmless",
        "result": "clean",
        "method": "blacklist",
        "engine_name": "Trustwave"
      },
      "CyRadar": {
        "category": "malicious",
        "result": "malicious",
        "method": "blacklist",
        "engine_name": "CyRadar"
      },
      "Dr.Web": {
        "category": "harmless",
        "result": "clean",
        "method": "blacklist",
        "engine_name": "Dr.Web"
      },
      "Emsisoft": {
        "category": "harmless",
        "result": "clean",
        "method": "blacklist",
        "engine_name": "Emsisoft"
      },
      "Abusix": {
        "category": "harmless",
        "result": "clean",
        "method": "blacklist",
        "engine_name": "Abusix"
      },
      "Webroot": {
        "category": "harmless",
        "result": "clean",
        "method": "blacklist",
        "engine_name": "Webroot"
      },
      "Avira": {
        "category": "harmless",
        "result": "clean",
        "method": "blacklist",
        "engine_name": "Avira"
      },
      "securolytics": {
        "category": "harmless",
        "result": "clean",
        "method": "blacklist",
        "engine_name": "securolytics"
      },
      "Antiy-AVL": {
        "category": "harmless",
        "result": "clean",
        "method": "blacklist",
        "engine_name": "Antiy-AVL"
      },
      "AlphaSOC": {
        "category": "undetected",
        "result": "unrated",
        "method": "blacklist",
        "engine_name": "AlphaSOC"
      },
      "Acronis": {
        "category": "harmless",
        "result": "clean",
        "method": "blacklist",
        "engine_name": "Acronis"
      },
      "Quick Heal": {
        "category": "harmless",
        "result": "clean",
        "method": "blacklist",
        "engine_name": "Quick Heal"
      },
      "URLQuery": {
        "category": "undetected",
        "result": "unrated",
        "method": "blacklist",
        "engine_name": "URLQuery"
      },
      "Ermes": {
        "category": "undetected",
        "result": "unrated",
        "method": "blacklist",
        "engine_name": "Ermes"
      },
      "Viettel Threat Intelligence": {
        "category": "harmless",
        "result": "clean",
        "method": "blacklist",
        "engine_name": "Viettel Threat Intelligence"
      },
      "DNS8": {
        "category": "harmless",
        "result": "clean",
        "method": "blacklist",
        "engine_name": "DNS8"
      },
      "AILabs (MONITORAPP)": {
        "category": "harmless",
        "result": "clean",
        "method": "blacklist",
        "engine_name": "AILabs (MONITORAPP)"
      },
      "benkow.cc": {
        "category": "harmless",
        "result": "clean",
        "method": "blacklist",
        "engine_name": "benkow.cc"
      },
      "EmergingThreats": {
        "category": "harmless",
        "result": "clean",
        "method": "blacklist",
        "engine_name": "EmergingThreats"
      },
      "Chong Lua Dao": {
        "category": "harmless",
        "result": "clean",
        "method": "blacklist",
        "engine_name": "Chong Lua Dao"
      },
      "Yandex Safebrowsing": {
        "category": "harmless",
        "result": "clean",
        "method": "blacklist",
        "engine_name": "Yandex Safebrowsing"
      },
      "Lumu": {
        "category": "undetected",
        "result": "unrated",
        "method": "blacklist",
        "engine_name": "Lumu"
      },
      "zvelo": {
        "category": "undetected",
        "result": "unrated",
        "method": "blacklist",
        "engine_name": "zvelo"
      },
      "Kaspersky": {
        "category": "undetected",
        "result": "unrated",
        "method": "blacklist",
        "engine_name": "Kaspersky"
      },
      "Segasec": {
        "category": "undetected",
        "result": "unrated",
        "method": "blacklist",
        "engine_name": "Segasec"
      },
      "Sucuri SiteCheck": {
        "category": "harmless",
        "result": "clean",
        "method": "blacklist",
        "engine_name": "Sucuri SiteCheck"
      },
      "desenmascara.me": {
        "category": "harmless",
        "result": "clean",
        "method": "blacklist",
        "engine_name": "desenmascara.me"
      },
      "CrowdSec": {
        "category": "undetected",
        "result": "unrated",
        "method": "blacklist",
        "engine_name": "CrowdSec"
      },
      "Cluster25": {
        "category": "undetected",
        "result": "unrated",
        "method": "blacklist",
        "engine_name": "Cluster25"
      },
      "SOCRadar": {
        "category": "suspicious",
        "result": "suspicious",
        "method": "blacklist",
        "engine_name": "SOCRadar"
      },
      "URLhaus": {
        "category": "harmless",
        "result": "clean",
        "method": "blacklist",
        "engine_name": "URLhaus"
      },
      "PREBYTES": {
        "category": "harmless",
        "result": "clean",
        "method": "blacklist",
        "engine_name": "PREBYTES"
      },
      "StopForumSpam": {
        "category": "harmless",
        "result": "clean",
        "method": "blacklist",
        "engine_name": "StopForumSpam"
      },
      "Blueliv": {
        "category": "harmless",
        "result": "clean",
        "method": "blacklist",
        "engine_name": "Blueliv"
      },
      "Netcraft": {
        "category": "undetected",
        "result": "unrated",
        "method": "blacklist",
        "engine_name": "Netcraft"
      },
      "ZeroCERT": {
        "category": "harmless",
        "result": "clean",
        "method": "blacklist",
        "engine_name": "ZeroCERT"
      },
      "Phishing Database": {
        "category": "harmless",
        "result": "clean",
        "method": "blacklist",
        "engine_name": "Phishing Database"
      },
      "MalwarePatrol": {
        "category": "harmless",
        "result": "clean",
        "method": "blacklist",
        "engine_name": "MalwarePatrol"
      },
      "IPsum": {
        "category": "harmless",
        "result": "clean",
        "method": "blacklist",
        "engine_name": "IPsum"
      },
      "Malwared": {
        "category": "harmless",
        "result": "clean",
        "method": "blacklist",
        "engine_name": "Malwared"
      },
      "BitDefender": {
        "category": "harmless",
        "result": "clean",
        "method": "blacklist",
        "engine_name": "BitDefender"
      },
      "GreenSnow": {
        "category": "harmless",
        "result": "clean",
        "method": "blacklist",
        "engine_name": "GreenSnow"
      },
      "G-Data": {
        "category": "harmless",
        "result": "clean",
        "method": "blacklist",
        "engine_name": "G-Data"
      },
      "VIPRE": {
        "category": "undetected",
        "result": "unrated",
        "method": "blacklist",
        "engine_name": "VIPRE"
      },
      "SCUMWARE.org": {
        "category": "harmless",
        "result": "clean",
        "method": "blacklist",
        "engine_name": "SCUMWARE.org"
      },
      "PhishFort": {
        "category": "undetected",
        "result": "unrated",
        "method": "blacklist",
        "engine_name": "PhishFort"
      },
      "malwares.com URL checker": {
        "category": "harmless",
        "result": "clean",
        "method": "blacklist",
        "engine_name": "malwares.com URL checker"
      },
      "Forcepoint ThreatSeeker": {
        "category": "undetected",
        "result": "unrated",
        "method": "blacklist",
        "engine_name": "Forcepoint ThreatSeeker"
      },
      "Criminal IP": {
        "category": "malicious",
        "result": "malicious",
        "method": "blacklist",
        "engine_name": "Criminal IP"
      },
      "Certego": {
        "category": "harmless",
        "result": "clean",
        "method": "blacklist",
        "engine_name": "Certego"
      },
      "ESET": {
        "category": "harmless",
        "result": "clean",
        "method": "blacklist",
        "engine_name": "ESET"
      },
      "Threatsourcing": {
        "category": "harmless",
        "result": "clean",
        "method": "blacklist",
        "engine_name": "Threatsourcing"
      },
      "ThreatHive": {
        "category": "harmless",
        "result": "clean",
        "method": "blacklist",
        "engine_name": "ThreatHive"
      },
      "Bfore.Ai PreCrime": {
        "category": "harmless",
        "result": "clean",
        "method": "blacklist",
        "engine_name": "Bfore.Ai PreCrime"
      }
    },
    "country": "BG",
    "last_modification_date": 1694449037,
    "regional_internet_registry": "RIPE NCC",
    "last_https_certificate": {
      "public_key": {
        "rsa": {
          "key_size": 1024,
          "modulus": "a5b8be1a9eb39eb38a1b34e82c6dba209f06d3ffdb8d1c50d63064eeef3a778bef68eb875d13f6ee02fa7d0d7657fc41524635d6e3dbd7826083046918d1046860f90b653c78a94a92be2d8065f5bbff09d35416aafbcfdc62fe0991432bff05943d23f87021a40d784e3d0e0db724e3e85d2d150093388146fbb3426979edc3",
          "exponent": "10001"
        },
        "algorithm": "RSA"
      },
      "thumbprint_sha256": "a3169659885f20031148d1f12a3ac72fd5c9c1cdc4e024edc70c5943f770444e",
      "thumbprint": "190a3d0c9bd647835454697dd351e06d3f5b3092",
      "subject": {
        "C": "US",
        "CN": "bc:67:1c:f7:0c:f0",
        "L": "Irvine",
        "O": "Cisco Systems, Inc.",
        "ST": "Califomia",
        "OU": "RV325"
      },
      "validity": {
        "not_after": "2022-11-09 01:01:01",
        "not_before": "2012-11-11 01:01:01"
      },
      "version": "V3",
      "extensions": {
        "subject_key_identifier": "ef90fa86fa15789bf00da3c4c1aba7edc58aa12f",
        "CA": true,
        "authority_key_identifier": {
          "keyid": "ef90fa86fa15789bf00da3c4c1aba7edc58aa12f"
        }
      },
      "cert_signature": {
        "signature_algorithm": "1.2.840.113549.1.1.5",
        "signature": "1c0c8ed4f93d4d2e4603330cd8a43c1bd4267eba6eaab485958a7f618d5890da444bcf295a3160e3777fcd375bae564fb55b12b012b3dbc60c9cfd9cbcf9d30942a5dc6cba73ced809561b145824670c8b2b6d7ed44dece8ca5fc8541e4fb05f5577a7a64de95fbdd7a3add89461d18ed7b946fce2e1aa72241c348f71238d08"
      },
      "serial_number": "bfe4069d3a16adf1",
      "issuer": {
        "C": "US",
        "CN": "bc:67:1c:f7:0c:f0",
        "L": "Irvine",
        "O": "Cisco Systems, Inc.",
        "ST": "Califomia",
        "OU": "RV325"
      },
      "size": 714
    },
    "continent": "EU",
    "total_votes": {
      "harmless": 0,
      "malicious": 0
    }
  },
  "type": "ip_address",
  "id": "84.238.197.36",
  "links": {
    "self": "https://www.virustotal.com/api/v3/ip_addresses/84.238.197.36"
  }
}